pbc/__init__.py
pbc/bin.py
pbc/phira_chart.py
pbc/utils/__init__.py
pbc/utils/fraction.py
pbc_sjfhsjfh-0.0.6.dist-info/METADATA
pbc_sjfhsjfh-0.0.6.dist-info/WHEEL
pbc_sjfhsjfh-0.0.6.dist-info/licenses/LICENSE
pbc_sjfhsjfh-0.0.6.dist-info/RECORD
