Metadata-Version: 2.3
Name: pbc_sjfhsjfh
Version: 0.0.6
Summary: Phira chart structure package
Project-URL: Homepage, https://github.com/TeamFlos/pbc
Author-email: sjfhsjfh <sjfhsjfh@qq.com>
License-File: LICENSE
Classifier: License :: OSI Approved :: MIT License
Classifier: Operating System :: OS Independent
Classifier: Programming Language :: Python :: 3
Requires-Python: >=3.11
